README.rst
setup.py
flask_gcp_log_groups/__init__.py
flask_gcp_log_groups/background_thread.py
flask_gcp_log_groups/gcp_logging.py
flask_gcp_log_groups.egg-info/PKG-INFO
flask_gcp_log_groups.egg-info/SOURCES.txt
flask_gcp_log_groups.egg-info/dependency_links.txt
flask_gcp_log_groups.egg-info/requires.txt
flask_gcp_log_groups.egg-info/top_level.txt