Metadata-Version: 1.1
Name: flask-gcp-log-groups
Version: 0.0.9
Summary: Python Flask logging handler to group messages on Google Cloud Platform
Home-page: https://github.com/salrashid123/flask-gcp-log-groups
Author: Sal Rashid
Author-email: salrashid123@gmail.com
License: UNKNOWN
Platform: UNKNOWN
Classifier: License :: OSI Approved :: Apache Software License
Classifier: Operating System :: OS Independent
Classifier: Development Status :: 3 - Alpha
Classifier: Intended Audience :: Developers
Classifier: Programming Language :: Python
Classifier: Programming Language :: Python :: 2.7
Classifier: Programming Language :: Python :: 3.0
Classifier: Topic :: Software Development :: Libraries
Classifier: Topic :: Software Development :: Libraries :: Python Modules
Classifier: Topic :: System :: Logging
